{
  "name": "Sophie Burgess",
  "age": 18,
  "address": {
    "street": "Cisoj Extension",
    "city": "Mesurgi",
    "state": "KY",
    "zip": "10993"
  },
  "contact": {
    "phone": "(273) 644-2747",
    "servicePhone": "800387324"
  },
  "birthday": "1984-02-26T10:50:11.147Z",
  "ip": "49.34.247.3",
  "foo": "bar",
  "profile": {
    "about": "Dartomi azturve dikudze oj fujad hoju wir sak hegocbir moevine vuoj vuwpi huor. Ofgu tu siak nemaz gilo ru kepacoh tiwgebe ozjun huubu zebvokzap awmiswab za wofohsuh ananiep ugaivdu mub. Ejawuza gosnet fom finu rurwi numa befe naje ino asapokof vacu pewos abzez lucka jo sufizi. Ogo bid fuceza kul cukuzasuz binbi kew patok humiwo fitpeg vul cam masoj. Of tezawig kehiifa uttumnu teletbaf huza zusu uz hefi poc bokbo ilvu gi he tucge. Bo nud gutrupih joad bup kim odbaj baveim uli azifub giscov ug. Ralo le kovril sihluw ese farac gu acuave dovber mutgi ram uzcik avolahfi aliwaoza pij.",
    "bio": "Oho ni rocli novibuure gisa awumoni alici ito sucviwin bemup onpijfiw sojdadiz roj dejoc. Apgo wil bipek cakour we ujulur mo goltibo ome neuf ligcutob alsefu ebaenahaf egsu tiwima zinew odki noz. Ut zowir egojobdeg tebova foftisib zi ib sowdilli kof emu likgocmog ganaha."
  },
  "apiKey": "8f70ee17171802ed2c3a320aa9a2f90c6bec11e1b70a21762ea6e82d1195bb59",
  "currency": {
    "code": "TJS",
    "name": "Tajikistan Somoni"
  }
}